qc_syn/__init__.py
qc_syn/envs/__init__.py
qc_syn/envs/quantum_circuit.py
qc_syn-0.1.0.dist-info/LICENSE
qc_syn-0.1.0.dist-info/METADATA
qc_syn-0.1.0.dist-info/WHEEL
qc_syn-0.1.0.dist-info/top_level.txt
qc_syn-0.1.0.dist-info/RECORD
