Metadata-Version: 2.1
Name: qc_syn
Version: 0.1.0
Summary: A quantum circuit synthesis environment for reinforcement learning
Home-page: https://github.com/michaelkoelle/rl-qc-syn
Author: Michael Kölle
Author-email: michael.koelle@ifi.lmu.de
Classifier: Programming Language :: Python :: 3
Classifier: License :: OSI Approved :: MIT License
Classifier: Operating System :: OS Independent
Requires-Python: >=3.8
License-File: LICENSE
Requires-Dist: gymnasium ==0.28.1
Requires-Dist: numpy ==1.23.5
Requires-Dist: PennyLane ==0.29.1
